_CRFPP.cpython-37m-x86_64-linux-gnu.so
CRFPP.py
crfpy/test.py
crfpy/learn.py
crfpy-0.0.0.3.dist-info/METADATA
crfpy-0.0.0.3.dist-info/top_level.txt
crfpy-0.0.0.3.dist-info/WHEEL
crfpy-0.0.0.3.dist-info/entry_points.txt
crfpy-0.0.0.3.dist-info/RECORD
