Metadata-Version: 2.1
Name: crfpy
Version: 0.0.0.3
Summary: Python binding for crfpp(CRF++)
Home-page: https://github.com/seifer08ms/crfpy
Author: Chenliang Wang
Author-email: chenliangwang08ms@gmail.com
Keywords: CRF Wrapper CRF++ crfpp module nlp
Classifier: Development Status :: 3 - Alpha
Classifier: Operating System :: OS Independent
Classifier: Intended Audience :: Developers
Classifier: License :: OSI Approved :: BSD License
Classifier: Programming Language :: Python
Classifier: Programming Language :: Python :: Implementation
Classifier: Programming Language :: Python :: 3
Classifier: Programming Language :: Python :: 3.7
Classifier: Programming Language :: Python :: 3.8
Classifier: Programming Language :: Python :: 3.9
Classifier: Topic :: Software Development :: Libraries
Requires-Python: >=2.7
